<?xml version="1.0" encoding="UTF-8"?>
<objects serializationModel="Studio.02.02.00">
    <object class="EncodingSetting" id="{b07c80c2-31d9-44ed-b598-c7d4bdfcb379}">
        <property name="encodingFormat">
            <value>3</value>
        </property>
        <property name="quality">
            <value>37</value>
        </property>
        <relationship name="platform">
            <destination>{0404a294-51e1-4ebc-a235-28184503fc55}</destination>
        </relationship>
        <relationship name="encodable">
            <destination>{0404a294-51e1-4ebc-a235-28184503fc55}</destination>
        </relationship>
    </object>
</objects>